unit4/__init__.py
unit4/core.py
unit4/unit4.py
unit4-0.0.2.dist-info/LICENSE
unit4-0.0.2.dist-info/METADATA
unit4-0.0.2.dist-info/WHEEL
unit4-0.0.2.dist-info/top_level.txt
unit4-0.0.2.dist-info/RECORD
