Metadata-Version: 2.1
Name: unit4
Version: 0.0.2
Summary: Package for pulling datasets using the Unit4 Multivers API
Home-page: https://github.com/zypp-io/sampleproject
Author: Melvin Folkers (Zyp)
Author-email: melvin@zypp.io, hello@zypp.io
License: UNKNOWN
Project-URL: Bug Tracker, https://github.com/zypp-io/unit4/issues
Project-URL: Source, https://github.com/zypp-io/unit4
Keywords: python,sampleproject
Platform: UNKNOWN
Classifier: Programming Language :: Python :: 3
Classifier: License :: OSI Approved :: MIT License
Classifier: Operating System :: OS Independent
Requires-Python: >=3.7
License-File: LICENSE
Requires-Dist: pandas (==1.3.4)
Requires-Dist: requests (==2.26.0)
